MONet/__init__.py
MONet/_version.py
MONet/auth.py
MONet/utils.py
MONet/icons/Concatenate.png
MONet/icons/Home-icon.svg.png
MONet/icons/Local.png
MONet/icons/Models.png
MONet/icons/Remote.png
MONet/icons/__init__.py
MONet/icons/logo.svg
MONet_scripts/MAIA_QR.py
MONet_scripts/MAIA_Segmentation_Portal.py
MONet_scripts/MONet_MONAI_Label.py
MONet_scripts/MONet_PL.py
MONet_scripts/MONet_concatenate_modalities.py
MONet_scripts/MONet_convert_ckpt_to_ts.py
MONet_scripts/MONet_convert_nnunet_checkpoint_to_bundle_checkpoint.py
MONet_scripts/MONet_fetch_bundle.py
MONet_scripts/MONet_inference_dicom.py
MONet_scripts/MONet_inference_nifti.py
MONet_scripts/MONet_local_inference.py
MONet_scripts/MONet_login.py
MONet_scripts/MONet_pipeline.py
MONet_scripts/MONet_remote_inference.py
MONet_scripts/MONet_run_conversion.py
MONet_scripts/__init__.py
monet_bundle-1.3.data/data/requirements.txt
monet_bundle-1.3.dist-info/licenses/LICENSE
monet_bundle-1.3.dist-info/METADATA
monet_bundle-1.3.dist-info/WHEEL
monet_bundle-1.3.dist-info/entry_points.txt
monet_bundle-1.3.dist-info/top_level.txt
monet_bundle-1.3.dist-info/RECORD
