Metadata-Version: 2.4
Name: monet-bundle
Version: 1.3
Summary: A Python package providing the MONet Bundle for nnUNet, extending it with MONAI functionalities and access to the MAIA Segmentation Portal.
Home-page: https://github.com/SimoneBendazzoli93/MONet-Bundle.git
Author: Bendazzoli Simone
Author-email: simben@kth.se
License: GPLv3
Project-URL: Documentation, https://monet-bundle.readthedocs.io
Project-URL: Bug Tracker, https://github.com/SimoneBendazzoli93/MONet-Bundle/issues
Project-URL: Source Code, https://github.com/SimoneBendazzoli93/MONet-Bundle
Keywords: monai,model inference,pytorch,monet bundle,maia
Platform: OS Independent
Requires-Python: >=3.10
License-File: LICENSE
Requires-Dist: nnunetv2
Requires-Dist: monai
Requires-Dist: nvflare
Requires-Dist: PyJWT
Requires-Dist: python-on-whales
Requires-Dist: SimpleITK
Requires-Dist: PyQt5
Requires-Dist: requests
Dynamic: keywords
Dynamic: license-file
